itg/__init__.py
itg/io/__init__.py
itg/utils/__init__.py
itg/utils/math/__init__.py
itg/utils/math/swsh.py
itgpy-0.1.1.dist-info/METADATA
itgpy-0.1.1.dist-info/WHEEL
itgpy-0.1.1.dist-info/top_level.txt
itgpy-0.1.1.dist-info/RECORD
